twilio_webhooks/__init__.py
twilio_webhooks/fax.py
twilio_webhooks/sms.py
twilio_webhooks/utils.py
twilio_webhooks-0.1.0.dist-info/LICENSE
twilio_webhooks-0.1.0.dist-info/METADATA
twilio_webhooks-0.1.0.dist-info/WHEEL
twilio_webhooks-0.1.0.dist-info/top_level.txt
twilio_webhooks-0.1.0.dist-info/RECORD
