Metadata-Version: 2.1
Name: twilio-webhooks
Version: 0.1.0
Summary: A collection of webhooks for Twilio using Flask.
Home-page: https://github.com/michael-lorenzo/twilio-webhooks
Author: Michael Lorenzo
Author-email: python@michael-lorenzo.com
License: UNKNOWN
Platform: UNKNOWN
Classifier: Programming Language :: Python :: 3
Classifier: License :: OSI Approved :: Apache Software License
Classifier: Operating System :: OS Independent
Requires-Python: >=3.6
Requires-Dist: flask
Requires-Dist: twilio
